hamsterkombat_clicker/__init__.py
hamsterkombat_clicker/clicker.py
hamsterkombat_clicker-0.1.0.dist-info/LICENSE
hamsterkombat_clicker-0.1.0.dist-info/METADATA
hamsterkombat_clicker-0.1.0.dist-info/WHEEL
hamsterkombat_clicker-0.1.0.dist-info/top_level.txt
hamsterkombat_clicker-0.1.0.dist-info/RECORD
