Metadata-Version: 2.1
Name: hamsterkombat_clicker
Version: 0.1.0
Summary: A package to interact with the Hamster Kombat Clicker API.
Home-page: https://github.com/Diyarbekoralbaev/hamsterkombat_clicker
Author: Diyarbek Oralbaev
Author-email: diyarbekdev@gmail.com
Classifier: Programming Language :: Python :: 3
Classifier: License :: OSI Approved :: MIT License
Classifier: Operating System :: OS Independent
Requires-Python: >=3.6
License-File: LICENSE
Requires-Dist: requests
